main.py
yfinance_mcp_server-1.0.4.dist-info/licenses/LICENSE
yfinance_mcp_server-1.0.4.dist-info/METADATA
yfinance_mcp_server-1.0.4.dist-info/WHEEL
yfinance_mcp_server-1.0.4.dist-info/entry_points.txt
yfinance_mcp_server-1.0.4.dist-info/top_level.txt
yfinance_mcp_server-1.0.4.dist-info/RECORD
