Metadata-Version: 2.4
Name: yfinance-mcp-server
Version: 1.0.4
Summary: A comprehensive yfinance MCP server providing access to Yahoo Finance data
Author-email: Jayesh <jaypatel6963@gmail.com>
License-Expression: MIT
Project-URL: Homepage, https://github.com/yourusername/yfinance-mcp-server
Project-URL: Bug Reports, https://github.com/yourusername/yfinance-mcp-server/issues
Project-URL: Source, https://github.com/yourusername/yfinance-mcp-server
Keywords: mcp,model-context-protocol,yfinance,yahoo-finance,stocks,financial-data
Classifier: Development Status :: 4 - Beta
Classifier: Intended Audience :: Developers
Classifier: Operating System :: OS Independent
Classifier: Programming Language :: Python :: 3
Classifier: Programming Language :: Python :: 3.10
Classifier: Programming Language :: Python :: 3.11
Classifier: Programming Language :: Python :: 3.12
Classifier: Topic :: Office/Business :: Financial
Classifier: Topic :: Software Development :: Libraries :: Python Modules
Requires-Python: >=3.10
License-File: LICENSE
Requires-Dist: yfinance
Requires-Dist: fastmcp
Requires-Dist: pandas
Dynamic: license-file
